sdif/__init__.py
sdif/fields.py
sdif/model_meta.py
sdif/models.py
sdif/py.typed
sdif/records.py
sdif/time.py
sdif-24.2.1.post0.dist-info/LICENSE
sdif-24.2.1.post0.dist-info/METADATA
sdif-24.2.1.post0.dist-info/WHEEL
sdif-24.2.1.post0.dist-info/top_level.txt
sdif-24.2.1.post0.dist-info/RECORD
