Metadata-Version: 2.1
Name: sdif
Version: 24.2.1.post0
Summary: Support for US Swimming SDIF v3 files
Author-email: "Tim D. Smith" <tim@tds.xyz>
Project-URL: repository, https://github.com/tdsmith/sdif
Classifier: License :: OSI Approved :: Apache Software License
Requires-Python: >=3.9
License-File: LICENSE
Requires-Dist: attrs
Requires-Dist: typing-extensions
Requires-Dist: typing-inspect
Provides-Extra: dev
Requires-Dist: black ; extra == 'dev'
Requires-Dist: isort ; extra == 'dev'
Requires-Dist: pip-tools ; extra == 'dev'
Requires-Dist: pyright ; extra == 'dev'
Requires-Dist: pytest ; extra == 'dev'
